nni
nni_annotation
nni_cmd
nni_gpu_tool
nni_plot
nni_trial_tool
