Metadata-Version: 2.1
Name: xnni
Version: 0.7
Summary: Neural Network Intelligence package for nitrogen
Home-page: https://github.com/Microsoft/nni
Author: XARC team
Author-email: shiqi.lu@xtalpi.com
License: MIT
Platform: UNKNOWN
Classifier: Programming Language :: Python :: 3
Classifier: License :: OSI Approved :: MIT License
Classifier: Operating System :: POSIX :: Linux
Requires-Python: >=3.5
Requires-Dist: schema
Requires-Dist: ruamel.yaml
Requires-Dist: psutil
Requires-Dist: requests
Requires-Dist: astor
Requires-Dist: PythonWebHDFS
Requires-Dist: hyperopt
Requires-Dist: json-tricks
Requires-Dist: numpy
Requires-Dist: scipy
Requires-Dist: coverage
Requires-Dist: colorama
Requires-Dist: pandas
Requires-Dist: pyecharts
